PrettyPrints/__init__.py
PrettyPrints/prettyprints.py
PrettyPrints-2.0.2.dist-info/LICENSE
PrettyPrints-2.0.2.dist-info/METADATA
PrettyPrints-2.0.2.dist-info/WHEEL
PrettyPrints-2.0.2.dist-info/top_level.txt
PrettyPrints-2.0.2.dist-info/RECORD
