Metadata-Version: 2.1
Name: PrettyPrints
Version: 2.0.2
Summary: The lazy way for pretty print spacings.
Home-page: https://github.com/salhol/PrettyPrints
Author: Sally Holm
Author-email: sallymholm+github@gmail.com
License: glp-3.0-or-later
Platform: UNKNOWN
Classifier: License :: OSI Approved :: GNU General Public License v3 or later (GPLv3+)
Classifier: Programming Language :: Python :: 3.9
License-File: LICENSE
